pytest_doorstop.py
pytest_doorstop-1.0.0.dist-info/LICENSE
pytest_doorstop-1.0.0.dist-info/METADATA
pytest_doorstop-1.0.0.dist-info/WHEEL
pytest_doorstop-1.0.0.dist-info/entry_points.txt
pytest_doorstop-1.0.0.dist-info/top_level.txt
pytest_doorstop-1.0.0.dist-info/RECORD
