Metadata-Version: 2.1
Name: pytest-doorstop
Version: 1.0.0
Summary: A pytest plugin for adding test results into doorstop items.
Home-page: https://github.com/scuriosity/pytest-doorstop
Author: Andrew Simon
Author-email: asimon1@protonmail.com
Maintainer: Andrew Simon
Maintainer-email: asimon1@protonmail.com
License: GNU GPL v3.0
Platform: UNKNOWN
Classifier: Development Status :: 4 - Beta
Classifier: Framework :: Pytest
Classifier: Intended Audience :: Developers
Classifier: Topic :: Software Development :: Testing
Classifier: Programming Language :: Python
Classifier: Programming Language :: Python :: 3
Classifier: Programming Language :: Python :: 3.7
Classifier: Programming Language :: Python :: 3.8
Classifier: Operating System :: OS Independent
Classifier: License :: OSI Approved :: GNU General Public License v3 (GPLv3)
Requires-Python: >=3.7
Requires-Dist: pytest (>=3.5.0)
Requires-Dist: doorstop (>=2)
Requires-Dist: gitpython (>=3)
